lasagna/__init__.py
lasagna/agent_runner.py
lasagna/agent_util.py
lasagna/caching.py
lasagna/easy.py
lasagna/known_models.py
lasagna/known_providers.py
lasagna/lasagna_anthropic.py
lasagna/lasagna_bedrock.py
lasagna/lasagna_nvidia.py
lasagna/lasagna_ollama.py
lasagna/lasagna_openai.py
lasagna/mock_provider.py
lasagna/py.typed
lasagna/pydantic_util.py
lasagna/registrar.py
lasagna/stream.py
lasagna/tools_util.py
lasagna/tui.py
lasagna/types.py
lasagna/util.py
lasagna/planner/__init__.py
lasagna/planner/agent.py
lasagna/planner/debug_model.py
lasagna/planner/default_prompts.py
lasagna/planner/util.py
lasagna_ai-0.19.0.dist-info/METADATA
lasagna_ai-0.19.0.dist-info/WHEEL
lasagna_ai-0.19.0.dist-info/licenses/LICENSE.txt
lasagna_ai-0.19.0.dist-info/RECORD
