Metadata-Version: 2.4
Name: lasagna-ai
Version: 0.19.0
Summary: Layered agents!
Project-URL: Documentation, https://lasagna-ai.rhobota.com/
Project-URL: Issues, https://github.com/Rhobota/lasagna-ai/issues
Project-URL: Source, https://github.com/Rhobota/lasagna-ai
Author-email: Ryan Henning <ryan@rhobota.com>
License-File: LICENSE.txt
Keywords: agent,agents,ai,hierarchical,layered,layers,llm
Classifier: Intended Audience :: Developers
Classifier: Intended Audience :: Science/Research
Classifier: License :: OSI Approved :: MIT License
Classifier: Operating System :: MacOS
Classifier: Operating System :: Microsoft :: Windows
Classifier: Operating System :: POSIX :: Linux
Classifier: Programming Language :: Python
Classifier: Programming Language :: Python :: 3.8
Classifier: Programming Language :: Python :: 3.9
Classifier: Programming Language :: Python :: 3.10
Classifier: Programming Language :: Python :: 3.11
Classifier: Programming Language :: Python :: 3.12
Classifier: Programming Language :: Python :: Implementation :: CPython
Classifier: Programming Language :: Python :: Implementation :: PyPy
Classifier: Topic :: Scientific/Engineering :: Artificial Intelligence
Classifier: Topic :: Software Development :: Libraries :: Python Modules
Classifier: Typing :: Typed
Requires-Python: >=3.8
Requires-Dist: aiohttp[speedups]
Requires-Dist: colorama
Requires-Dist: httpx
Requires-Dist: openai<=1.99.9,>=1.52.0
Requires-Dist: pydantic<3,>=2.7
Requires-Dist: python-dotenv
Requires-Dist: svs
Provides-Extra: anthropic
Requires-Dist: anthropic<=0.64.0,>=0.37.1; extra == 'anthropic'
Provides-Extra: bedrock
Requires-Dist: boto3>=1.37.0; extra == 'bedrock'
Provides-Extra: dev
Requires-Dist: mypy>=1.10.0; extra == 'dev'
Requires-Dist: nbqa; extra == 'dev'
Requires-Dist: pytest-asyncio>=0.23.6; extra == 'dev'
Requires-Dist: pytest>=8.1.1; extra == 'dev'
Provides-Extra: example-deps
Requires-Dist: sympy; extra == 'example-deps'
Provides-Extra: openai
